{
  "method_name": "list_analyzers",
  "url": "https://boto3.amazonaws.com/v1/documentation/api/latest/reference/services/accessanalyzer/client/list_analyzers.html",
  "description": "Retrieves a list of analyzers.",
  "parameters": [
    {
      "name": "nextToken",
      "type": "string",
      "required": false,
      "description": "A token used for pagination of results returned.",
      "nested_params": []
    },
    {
      "name": "maxResults",
      "type": "integer",
      "required": false,
      "description": "The maximum number of results to return in the response.",
      "nested_params": []
    },
    {
      "name": "type",
      "type": "string",
      "required": false,
      "description": "The type of analyzer.",
      "nested_params": []
    }
  ],
  "return_structure": [
    {
      "name": "",
      "type": "dict",
      "description": "",
      "nested_items": [
        {
          "name": "analyzers",
          "type": "list",
          "description": "The analyzers retrieved.",
          "nested_items": [
            {
              "name": "",
              "type": "dict",
              "description": "",
              "nested_items": [
                {
                  "name": "arn",
                  "type": "string",
                  "description": "The ARN of the analyzer.",
                  "nested_items": []
                },
                {
                  "name": "name",
                  "type": "string",
                  "description": "The name of the analyzer.",
                  "nested_items": []
                },
                {
                  "name": "type",
                  "type": "string",
                  "description": "The type of analyzer, which corresponds to the zone of trust chosen for the analyzer.",
                  "nested_items": []
                },
                {
                  "name": "createdAt",
                  "type": "datetime",
                  "description": "A timestamp for the time at which the analyzer was created.",
                  "nested_items": []
                },
                {
                  "name": "lastResourceAnalyzed",
                  "type": "string",
                  "description": "The resource that was most recently analyzed by the analyzer.",
                  "nested_items": []
                },
                {
                  "name": "lastResourceAnalyzedAt",
                  "type": "datetime",
                  "description": "The time at which the most recently analyzed resource was analyzed.",
                  "nested_items": []
                },
                {
                  "name": "",
                  "type": "dict",
                  "description": "",
                  "nested_items": [
                    {
                      "name": "",
                      "type": "string",
                      "description": "(string) ---",
                      "nested_items": [
                        {
                          "name": "",
                          "type": "string",
                          "description": "(string) ---",
                          "nested_items": []
                        }
                      ]
                    }
                  ]
                },
                {
                  "name": "status",
                  "type": "string",
                  "description": "The status of the analyzer. An Active analyzer successfully monitors supported resources and generates new findings. The analyzer is Disabled when a user action, such as removing trusted access for Identity and Access Management Access Analyzer from Organizations, causes the analyzer to stop generating new findings. The status is Creating when the analyzer creation is in progress and Failed when the analyzer creation has failed.",
                  "nested_items": []
                },
                {
                  "name": "statusReason",
                  "type": "dict",
                  "description": "The statusReason provides more details about the current status of the analyzer. For example, if the creation for the analyzer fails, a Failed status is returned. For an analyzer with organization as the type, this failure can be due to an issue with creating the service-linked roles required in the member accounts of the Amazon Web Services organization.",
                  "nested_items": [
                    {
                      "name": "code",
                      "type": "string",
                      "description": "The reason code for the current status of the analyzer.",
                      "nested_items": []
                    }
                  ]
                },
                {
                  "name": "configuration",
                  "type": "dict",
                  "description": "Specifies whether the analyzer is an external access or unused access analyzer.",
                  "nested_items": [
                    {
                      "name": "unusedAccess",
                      "type": "dict",
                      "description": "Specifies the configuration of an unused access analyzer for an Amazon Web Services organization or account.",
                      "nested_items": [
                        {
                          "name": "unusedAccessAge",
                          "type": "integer",
                          "description": "The specified access age in days for which to generate findings for unused access. For example, if you specify 90 days, the analyzer will generate findings for IAM entities within the accounts of the selected organization for any access that hasn't been used in 90 or more days since the analyzer's last scan. You can choose a value between 1 and 365 days.",
                          "nested_items": []
                        },
                        {
                          "name": "analysisRule",
                          "type": "dict",
                          "description": "Contains information about analysis rules for the analyzer. Analysis rules determine which entities will generate findings based on the criteria you define when you create the rule.",
                          "nested_items": [
                            {
                              "name": "exclusions",
                              "type": "list",
                              "description": "A list of rules for the analyzer containing criteria to exclude from analysis. Entities that meet the rule criteria will not generate findings.",
                              "nested_items": [
                                {
                                  "name": "",
                                  "type": "dict",
                                  "description": "",
                                  "nested_items": [
                                    {
                                      "name": "accountIds",
                                      "type": "list",
                                      "description": "A list of Amazon Web Services account IDs to apply to the analysis rule criteria. The accounts cannot include the organization analyzer owner account. Account IDs can only be applied to the analysis rule criteria for organization-level analyzers. The list cannot include more than 2,000 account IDs.",
                                      "nested_items": [
                                        {
                                          "name": "",
                                          "type": "string",
                                          "description": "(string) ---",
                                          "nested_items": []
                                        }
                                      ]
                                    },
                                    {
                                      "name": "resourceTags",
                                      "type": "list",
                                      "description": "An array of key-value pairs to match for your resources. You can use the set of Unicode letters, digits, whitespace, _, ., /, =, +, and -.",
                                      "nested_items": [
                                        {
                                          "name": "",
                                          "type": "dict",
                                          "description": "",
                                          "nested_items": [
                                            {
                                              "name": "",
                                              "type": "string",
                                              "description": "(string) ---",
                                              "nested_items": [
                                                {
                                                  "name": "",
                                                  "type": "string",
                                                  "description": "(string) ---",
                                                  "nested_items": []
                                                }
                                              ]
                                            }
                                          ]
                                        }
                                      ]
                                    }
                                  ]
                                }
                              ]
                            }
                          ]
                        }
                      ]
                    }
                  ]
                }
              ]
            }
          ]
        },
        {
          "name": "nextToken",
          "type": "string",
          "description": "A token used for pagination of results returned.",
          "nested_items": []
        }
      ]
    }
  ]
}