{
  "method_name": "batch_update_bill_scenario_commitment_modification",
  "url": "https://boto3.amazonaws.com/v1/documentation/api/latest/reference/services/bcm-pricing-calculator/client/batch_update_bill_scenario_commitment_modification.html",
  "description": "Update a newly added or existing commitment. You can update the commitment group based on a commitment ID and a Bill scenario ID.",
  "parameters": [
    {
      "name": "billScenarioId",
      "type": "string",
      "required": true,
      "description": "The ID of the Bill Scenario for which you want to modify the commitment group of a modeled commitment.",
      "nested_params": []
    },
    {
      "name": "commitmentModifications",
      "type": "list",
      "required": true,
      "description": "List of commitments that you want to update in a Bill Scenario. (dict) --- Represents an entry in a batch operation to update bill scenario commitment modifications. The unique identifier of the commitment modification to update. group (string) --- The updated group identifier for the commitment modification.",
      "nested_params": [
        {
          "name": "id",
          "type": "string",
          "required": false,
          "description": "The unique identifier of the commitment modification to update.",
          "nested_params": []
        },
        {
          "name": "group",
          "type": "string",
          "required": false,
          "description": "The updated group identifier for the commitment modification.",
          "nested_params": []
        }
      ]
    }
  ],
  "return_structure": [
    {
      "name": "",
      "type": "dict",
      "description": "",
      "nested_items": [
        {
          "name": "items",
          "type": "list",
          "description": "Returns the list of successful commitment line items that were updated for a Bill Scenario.",
          "nested_items": [
            {
              "name": "",
              "type": "dict",
              "description": "",
              "nested_items": [
                {
                  "name": "id",
                  "type": "string",
                  "description": "The unique identifier of the commitment modification.",
                  "nested_items": []
                },
                {
                  "name": "usageAccountId",
                  "type": "string",
                  "description": "The Amazon Web Services account ID associated with this commitment modification.",
                  "nested_items": []
                },
                {
                  "name": "group",
                  "type": "string",
                  "description": "The group identifier for the commitment modification.",
                  "nested_items": []
                },
                {
                  "name": "commitmentAction",
                  "type": "dict",
                  "description": "The specific commitment action taken in this modification.",
                  "nested_items": [
                    {
                      "name": "addReservedInstanceAction",
                      "type": "dict",
                      "description": "Action to add a Reserved Instance to the scenario.",
                      "nested_items": [
                        {
                          "name": "reservedInstancesOfferingId",
                          "type": "string",
                          "description": "The ID of the Reserved Instance offering to add. For more information, see DescribeReservedInstancesOfferings.",
                          "nested_items": []
                        },
                        {
                          "name": "instanceCount",
                          "type": "integer",
                          "description": "The number of instances to add for this Reserved Instance offering.",
                          "nested_items": []
                        }
                      ]
                    },
                    {
                      "name": "addSavingsPlanAction",
                      "type": "dict",
                      "description": "Action to add a Savings Plan to the scenario.",
                      "nested_items": [
                        {
                          "name": "savingsPlanOfferingId",
                          "type": "string",
                          "description": "The ID of the Savings Plan offering to add. For more information, see DescribeSavingsPlansOfferings.",
                          "nested_items": []
                        },
                        {
                          "name": "commitment",
                          "type": "float",
                          "description": "The hourly commitment, in the same currency of the savingsPlanOfferingId. This is a value between 0.001 and 1 million. You cannot specify more than five digits after the decimal point.",
                          "nested_items": []
                        }
                      ]
                    },
                    {
                      "name": "negateReservedInstanceAction",
                      "type": "dict",
                      "description": "Action to remove a Reserved Instance from the scenario.",
                      "nested_items": [
                        {
                          "name": "reservedInstancesId",
                          "type": "string",
                          "description": "The ID of the Reserved Instance to remove.",
                          "nested_items": []
                        }
                      ]
                    },
                    {
                      "name": "negateSavingsPlanAction",
                      "type": "dict",
                      "description": "Action to remove a Savings Plan from the scenario.",
                      "nested_items": [
                        {
                          "name": "savingsPlanId",
                          "type": "string",
                          "description": "The ID of the Savings Plan to remove.",
                          "nested_items": []
                        }
                      ]
                    }
                  ]
                }
              ]
            }
          ]
        },
        {
          "name": "errors",
          "type": "list",
          "description": "Returns the list of error reasons and commitment line item IDs that could not be updated for the Bill Scenario.",
          "nested_items": [
            {
              "name": "",
              "type": "dict",
              "description": "",
              "nested_items": [
                {
                  "name": "id",
                  "type": "string",
                  "description": "The ID of the error.",
                  "nested_items": []
                },
                {
                  "name": "errorCode",
                  "type": "string",
                  "description": "The code associated with the error.",
                  "nested_items": []
                },
                {
                  "name": "errorMessage",
                  "type": "string",
                  "description": "The message that describes the error.",
                  "nested_items": []
                }
              ]
            }
          ]
        }
      ]
    }
  ]
}