{
  "method_name": "put_app_instance_user_expiration_settings",
  "url": "https://boto3.amazonaws.com/v1/documentation/api/latest/reference/services/chime-sdk-identity/client/put_app_instance_user_expiration_settings.html",
  "description": "Sets the number of days before the AppInstanceUser is automatically deleted.",
  "parameters": [
    {
      "name": "AppInstanceUserArn",
      "type": "string",
      "required": true,
      "description": "The ARN of the AppInstanceUser.",
      "nested_params": []
    },
    {
      "name": "ExpirationSettings",
      "type": "dict",
      "required": true,
      "description": "Settings that control the interval after which an AppInstanceUser is automatically deleted. The period in days after which an AppInstanceUser will be automatically deleted. Specifies the conditions under which an AppInstanceUser will expire.",
      "nested_params": [
        {
          "name": "ExpirationDays",
          "type": "integer",
          "required": false,
          "description": "The period in days after which an AppInstanceUser will be automatically deleted.",
          "nested_params": []
        },
        {
          "name": "ExpirationCriterion",
          "type": "string",
          "required": false,
          "description": "Specifies the conditions under which an AppInstanceUser will expire.",
          "nested_params": []
        }
      ]
    }
  ],
  "return_structure": [
    {
      "name": "",
      "type": "dict",
      "description": "",
      "nested_items": [
        {
          "name": "AppInstanceUserArn",
          "type": "string",
          "description": "The ARN of the AppInstanceUser.",
          "nested_items": []
        },
        {
          "name": "ExpirationSettings",
          "type": "dict",
          "description": "Settings that control the interval after which an AppInstanceUser is automatically deleted.",
          "nested_items": [
            {
              "name": "ExpirationDays",
              "type": "integer",
              "description": "The period in days after which an AppInstanceUser will be automatically deleted.",
              "nested_items": []
            },
            {
              "name": "ExpirationCriterion",
              "type": "string",
              "description": "Specifies the conditions under which an AppInstanceUser will expire.",
              "nested_items": []
            }
          ]
        }
      ]
    }
  ]
}