{
  "method_name": "list_memberships",
  "url": "https://boto3.amazonaws.com/v1/documentation/api/latest/reference/services/cleanrooms/client/list_memberships.html",
  "description": "Lists all memberships resources within the caller's account.",
  "parameters": [
    {
      "name": "nextToken",
      "type": "string",
      "required": false,
      "description": "",
      "nested_params": []
    },
    {
      "name": "maxResults",
      "type": "integer",
      "required": false,
      "description": "",
      "nested_params": []
    },
    {
      "name": "status",
      "type": "string",
      "required": false,
      "description": "",
      "nested_params": []
    }
  ],
  "return_structure": [
    {
      "name": "",
      "type": "dict",
      "description": "",
      "nested_items": [
        {
          "name": "nextToken",
          "type": "string",
          "description": "The pagination token that's used to fetch the next set of results.",
          "nested_items": []
        },
        {
          "name": "membershipSummaries",
          "type": "list",
          "description": "The list of memberships returned from the ListMemberships operation.",
          "nested_items": [
            {
              "name": "",
              "type": "dict",
              "description": "",
              "nested_items": [
                {
                  "name": "id",
                  "type": "string",
                  "description": "The unique ID for the membership's collaboration.",
                  "nested_items": []
                },
                {
                  "name": "arn",
                  "type": "string",
                  "description": "The unique ARN for the membership.",
                  "nested_items": []
                },
                {
                  "name": "collaborationArn",
                  "type": "string",
                  "description": "The unique ARN for the membership's associated collaboration.",
                  "nested_items": []
                },
                {
                  "name": "collaborationId",
                  "type": "string",
                  "description": "The unique ID for the membership's collaboration.",
                  "nested_items": []
                },
                {
                  "name": "collaborationCreatorAccountId",
                  "type": "string",
                  "description": "The identifier of the Amazon Web Services principal that created the collaboration. Currently only supports Amazon Web Services account ID.",
                  "nested_items": []
                },
                {
                  "name": "collaborationCreatorDisplayName",
                  "type": "string",
                  "description": "The display name of the collaboration creator.",
                  "nested_items": []
                },
                {
                  "name": "collaborationName",
                  "type": "string",
                  "description": "The name for the membership's collaboration.",
                  "nested_items": []
                },
                {
                  "name": "createTime",
                  "type": "datetime",
                  "description": "The time when the membership was created.",
                  "nested_items": []
                },
                {
                  "name": "updateTime",
                  "type": "datetime",
                  "description": "The time the membership metadata was last updated.",
                  "nested_items": []
                },
                {
                  "name": "status",
                  "type": "string",
                  "description": "The status of the membership.",
                  "nested_items": []
                },
                {
                  "name": "memberAbilities",
                  "type": "list",
                  "description": "The abilities granted to the collaboration member.",
                  "nested_items": [
                    {
                      "name": "",
                      "type": "string",
                      "description": "(string) ---",
                      "nested_items": []
                    }
                  ]
                },
                {
                  "name": "mlMemberAbilities",
                  "type": "dict",
                  "description": "Provides a summary of the ML abilities for the collaboration member.",
                  "nested_items": [
                    {
                      "name": "customMLMemberAbilities",
                      "type": "list",
                      "description": "The custom ML member abilities for a collaboration member.",
                      "nested_items": [
                        {
                          "name": "",
                          "type": "string",
                          "description": "(string) ---",
                          "nested_items": []
                        }
                      ]
                    }
                  ]
                },
                {
                  "name": "paymentConfiguration",
                  "type": "dict",
                  "description": "The payment responsibilities accepted by the collaboration member.",
                  "nested_items": [
                    {
                      "name": "queryCompute",
                      "type": "dict",
                      "description": "The payment responsibilities accepted by the collaboration member for query compute costs.",
                      "nested_items": [
                        {
                          "name": "isResponsible",
                          "type": "boolean",
                          "description": "Indicates whether the collaboration member has accepted to pay for query compute costs ( TRUE) or has not accepted to pay for query compute costs ( FALSE).",
                          "nested_items": [
                            {
                              "name": "",
                              "type": "",
                              "description": "If you set the value to FALSE but you are responsible to pay for query compute costs.",
                              "nested_items": []
                            },
                            {
                              "name": "",
                              "type": "",
                              "description": "If you set the value to TRUE but you are not responsible to pay for query compute costs.",
                              "nested_items": []
                            }
                          ]
                        }
                      ]
                    },
                    {
                      "name": "machineLearning",
                      "type": "dict",
                      "description": "The payment responsibilities accepted by the collaboration member for machine learning costs.",
                      "nested_items": [
                        {
                          "name": "modelTraining",
                          "type": "dict",
                          "description": "The payment responsibilities accepted by the member for model training.",
                          "nested_items": [
                            {
                              "name": "isResponsible",
                              "type": "boolean",
                              "description": "Indicates whether the collaboration member has accepted to pay for model training costs ( TRUE) or has not accepted to pay for model training costs ( FALSE).",
                              "nested_items": [
                                {
                                  "name": "",
                                  "type": "",
                                  "description": "If you set the value to FALSE but you are responsible to pay for model training costs.",
                                  "nested_items": []
                                },
                                {
                                  "name": "",
                                  "type": "",
                                  "description": "If you set the value to TRUE but you are not responsible to pay for model training costs.",
                                  "nested_items": []
                                }
                              ]
                            }
                          ]
                        },
                        {
                          "name": "modelInference",
                          "type": "dict",
                          "description": "The payment responsibilities accepted by the member for model inference.",
                          "nested_items": [
                            {
                              "name": "isResponsible",
                              "type": "boolean",
                              "description": "Indicates whether the collaboration member has accepted to pay for model inference costs ( TRUE) or has not accepted to pay for model inference costs ( FALSE).",
                              "nested_items": [
                                {
                                  "name": "",
                                  "type": "",
                                  "description": "If you set the value to FALSE but you are responsible to pay for model inference costs.",
                                  "nested_items": []
                                },
                                {
                                  "name": "",
                                  "type": "",
                                  "description": "If you set the value to TRUE but you are not responsible to pay for model inference costs.",
                                  "nested_items": []
                                }
                              ]
                            }
                          ]
                        }
                      ]
                    },
                    {
                      "name": "jobCompute",
                      "type": "dict",
                      "description": "The payment responsibilities accepted by the collaboration member for job compute costs.",
                      "nested_items": [
                        {
                          "name": "isResponsible",
                          "type": "boolean",
                          "description": "Indicates whether the collaboration member has accepted to pay for job compute costs ( TRUE) or has not accepted to pay for query and job compute costs ( FALSE).",
                          "nested_items": [
                            {
                              "name": "",
                              "type": "",
                              "description": "If you set the value to FALSE but you are responsible to pay for query and job compute costs.",
                              "nested_items": []
                            },
                            {
                              "name": "",
                              "type": "",
                              "description": "If you set the value to TRUE but you are not responsible to pay for query and job compute costs.",
                              "nested_items": []
                            }
                          ]
                        }
                      ]
                    }
                  ]
                }
              ]
            }
          ]
        }
      ]
    }
  ]
}