{
  "method_name": "get_random_password",
  "url": "https://boto3.amazonaws.com/v1/documentation/api/latest/reference/services/secretsmanager/client/get_random_password.html",
  "description": "Generates a random password. We recommend that you specify the maximum length and include every character type that the system you are generating a password for can support. By default, Secrets Manager uses uppercase and lowercase letters, numbers, and the following characters in passwords: !\\\"#$%&'()*+,-./:;<=>?@[\\\\]^_`{|}~ Secrets Manager generates a CloudTrail log entry when you call this action. Required permissions: secretsmanager:GetRandomPassword. For more information, see IAM policy actions for Secrets Manager and Authentication and access control in Secrets Manager.",
  "parameters": [
    {
      "name": "PasswordLength",
      "type": "integer",
      "required": false,
      "description": "",
      "nested_params": []
    },
    {
      "name": "ExcludeCharacters",
      "type": "string",
      "required": false,
      "description": "",
      "nested_params": []
    },
    {
      "name": "ExcludeNumbers",
      "type": "boolean",
      "required": false,
      "description": "",
      "nested_params": []
    },
    {
      "name": "ExcludePunctuation",
      "type": "boolean",
      "required": false,
      "description": "",
      "nested_params": []
    },
    {
      "name": "ExcludeUppercase",
      "type": "boolean",
      "required": false,
      "description": "",
      "nested_params": []
    },
    {
      "name": "ExcludeLowercase",
      "type": "boolean",
      "required": false,
      "description": "",
      "nested_params": []
    },
    {
      "name": "IncludeSpace",
      "type": "boolean",
      "required": false,
      "description": "",
      "nested_params": []
    },
    {
      "name": "RequireEachIncludedType",
      "type": "boolean",
      "required": false,
      "description": "",
      "nested_params": []
    }
  ],
  "return_structure": [
    {
      "name": "",
      "type": "dict",
      "description": "",
      "nested_items": [
        {
          "name": "RandomPassword",
          "type": "string",
          "description": "A string with the password.",
          "nested_items": []
        }
      ]
    }
  ]
}